{
    "Scenario": "APIM",
    "ConnectionType": "scc",
    "BTPHost": {
        "Name": "ca10",
        "IPAddress": ""
    },
    "SCCHost": {
        "Name": "CanadaCentral",
        "IPAddress": ""
    },
    "S4HHost": {
        "Name": "CanadaCentral",
        "IPAddress": "20.104.99.158"
    },
    "HTTPRequest": {
        "Url": "https://tfe-aws.apimanagement.ca10.hana.ondemand.com/API_SO_CANADACENTRAL_SCC/A_SalesOrder",
        "Username": "BPINST",
        "Password": "Replace with Password"
    }
}